__init__.py
_version.py
boosters/__init__.py
boosters/boosters.py
build/lib/__init__.py
build/lib/_version.py
build/lib/boosters/__init__.py
build/lib/boosters/boosters.py
build/lib/build/lib/__init__.py
build/lib/build/lib/_version.py
build/lib/build/lib/boosters/__init__.py
build/lib/build/lib/boosters/boosters.py
build/lib/build/lib/build/lib/__init__.py
build/lib/build/lib/build/lib/_version.py
build/lib/build/lib/build/lib/boosters/__init__.py
build/lib/build/lib/build/lib/boosters/boosters.py
build/lib/build/lib/build/lib/build/lib/__init__.py
build/lib/build/lib/build/lib/build/lib/_version.py
build/lib/build/lib/build/lib/build/lib/boosters/__init__.py
build/lib/build/lib/build/lib/build/lib/boosters/boosters.py
build/lib/build/lib/build/lib/build/lib/build/lib/__init__.py
build/lib/build/lib/build/lib/build/lib/build/lib/_version.py
build/lib/build/lib/build/lib/build/lib/build/lib/boosters/__init__.py
build/lib/build/lib/build/lib/build/lib/build/lib/boosters/boosters.py
build/lib/build/lib/build/lib/build/lib/build/lib/build/lib/__init__.py
build/lib/build/lib/build/lib/build/lib/build/lib/build/lib/_version.py
build/lib/build/lib/build/lib/build/lib/build/lib/build/lib/boosters/__init__.py
build/lib/build/lib/build/lib/build/lib/build/lib/build/lib/boosters/boosters.py
build/lib/build/lib/build/lib/build/lib/build/lib/build/lib/client/__init__.py
build/lib/build/lib/build/lib/build/lib/build/lib/build/lib/client/client.py
build/lib/build/lib/build/lib/build/lib/build/lib/build/lib/gui/__init__.py
build/lib/build/lib/build/lib/build/lib/build/lib/build/lib/gui/gui.py
build/lib/build/lib/build/lib/build/lib/build/lib/build/lib/openfs/__init__.py
build/lib/build/lib/build/lib/build/lib/build/lib/build/lib/openfs/_dependencies.py
build/lib/build/lib/build/lib/build/lib/build/lib/build/lib/openfs/_version.py
build/lib/build/lib/build/lib/build/lib/build/lib/build/lib/stores/__init__.py
openfs-1.0.2.dist-info/LICENSE
openfs-1.0.2.dist-info/METADATA
openfs-1.0.2.dist-info/WHEEL
openfs-1.0.2.dist-info/top_level.txt
openfs-1.0.2.dist-info/RECORD
