Metadata-Version: 2.1
Name: openfs
Version: 1.0.2
Summary: An S3 feature store client for data pipelines.
Author-email: xplainable pty ltd <contact@xplainable.io>
License: MIT License
Classifier: Programming Language :: Python :: 3.8
Classifier: Programming Language :: Python :: 3.9
Classifier: Programming Language :: Python :: 3.10
Classifier: Programming Language :: Python :: 3.11
Classifier: Operating System :: OS Independent
Requires-Python: >=3.8
License-File: LICENSE
Requires-Dist: boto3 (>=1.26.154)
Requires-Dist: botocore (>=1.29.154)
Requires-Dist: pandas (>=1.2.0)
Provides-Extra: gui
Requires-Dist: ipywidgets (>=8.0.0) ; extra == 'gui'
Requires-Dist: ipython ; extra == 'gui'
